{"frames":[{"filename":"buttonSelected","frame":{"x":0,"y":0,"w":190,"h":49},"rotated":false,"trimmed":false,"spriteSourceSize":{"x":0,"y":0,"w":190,"h":49},"sourceSize":{"w":190,"h":49}},{"filename":"element_red_diamond_glossy","frame":{"x":191,"y":198,"w":48,"h":48},"rotated":false,"trimmed":false,"spriteSourceSize":{"x":0,"y":0,"w":48,"h":48},"sourceSize":{"w":48,"h":48}},{"filename":"element_green_polygon_glossy","frame":{"x":0,"y":298,"w":48,"h":46},"rotated":false,"trimmed":false,"spriteSourceSize":{"x":0,"y":0,"w":48,"h":46},"sourceSize":{"w":48,"h":46}},{"filename":"element_green_rectangle_glossy","frame":{"x":0,"y":150,"w":64,"h":32},"rotated":false,"trimmed":false,"spriteSourceSize":{"x":0,"y":0,"w":64,"h":32},"sourceSize":{"w":64,"h":32}},{"filename":"element_grey_rectangle_glossy","frame":{"x":65,"y":150,"w":64,"h":32},"rotated":false,"trimmed":false,"spriteSourceSize":{"x":0,"y":0,"w":64,"h":32},"sourceSize":{"w":64,"h":32}},{"filename":"element_green_polygon","frame":{"x":49,"y":298,"w":48,"h":46},"rotated":false,"trimmed":false,"spriteSourceSize":{"x":0,"y":0,"w":48,"h":46},"sourceSize":{"w":48,"h":46}},{"filename":"element_red_diamond","frame":{"x":0,"y":249,"w":48,"h":48},"rotated":false,"trimmed":false,"spriteSourceSize":{"x":0,"y":0,"w":48,"h":48},"sourceSize":{"w":48,"h":48}},{"filename":"buttonDefault","frame":{"x":0,"y":50,"w":190,"h":49},"rotated":false,"trimmed":false,"spriteSourceSize":{"x":0,"y":0,"w":190,"h":49},"sourceSize":{"w":190,"h":49}},{"filename":"element_purple_rectangle_glossy","frame":{"x":0,"y":183,"w":64,"h":32},"rotated":false,"trimmed":false,"spriteSourceSize":{"x":0,"y":0,"w":64,"h":32},"sourceSize":{"w":64,"h":32}},{"filename":"element_grey_polygon_glossy","frame":{"x":98,"y":298,"w":48,"h":46},"rotated":false,"trimmed":false,"spriteSourceSize":{"x":0,"y":0,"w":48,"h":46},"sourceSize":{"w":48,"h":46}},{"filename":"element_purple_diamond","frame":{"x":49,"y":249,"w":48,"h":48},"rotated":false,"trimmed":false,"spriteSourceSize":{"x":0,"y":0,"w":48,"h":48},"sourceSize":{"w":48,"h":48}},{"filename":"element_purple_rectangle","frame":{"x":65,"y":183,"w":64,"h":32},"rotated":false,"trimmed":false,"spriteSourceSize":{"x":0,"y":0,"w":64,"h":32},"sourceSize":{"w":64,"h":32}},{"filename":"element_blue_diamond","frame":{"x":98,"y":249,"w":48,"h":48},"rotated":false,"trimmed":false,"spriteSourceSize":{"x":0,"y":0,"w":48,"h":48},"sourceSize":{"w":48,"h":48}},{"filename":"element_blue_diamond_glossy","frame":{"x":147,"y":249,"w":48,"h":48},"rotated":false,"trimmed":false,"spriteSourceSize":{"x":0,"y":0,"w":48,"h":48},"sourceSize":{"w":48,"h":48}},{"filename":"element_green_diamond_glossy","frame":{"x":196,"y":249,"w":48,"h":48},"rotated":false,"trimmed":false,"spriteSourceSize":{"x":0,"y":0,"w":48,"h":48},"sourceSize":{"w":48,"h":48}},{"filename":"element_blue_square","frame":{"x":130,"y":216,"w":32,"h":32},"rotated":false,"trimmed":false,"spriteSourceSize":{"x":0,"y":0,"w":32,"h":32},"sourceSize":{"w":32,"h":32}},{"filename":"element_red_rectangle","frame":{"x":0,"y":216,"w":64,"h":32},"rotated":false,"trimmed":false,"spriteSourceSize":{"x":0,"y":0,"w":64,"h":32},"sourceSize":{"w":64,"h":32}},{"filename":"buttonSelected_topleft","frame":{"x":163,"y":150,"w":12,"h":12},"rotated":false,"trimmed":false,"spriteSourceSize":{"x":0,"y":0,"w":12,"h":12},"sourceSize":{"w":12,"h":12}},{"filename":"buttonDefault_bottom","frame":{"x":163,"y":163,"w":12,"h":12},"rotated":false,"trimmed":false,"spriteSourceSize":{"x":0,"y":0,"w":12,"h":12},"sourceSize":{"w":12,"h":12}},{"filename":"buttonDefault_bottomleft","frame":{"x":176,"y":163,"w":12,"h":12},"rotated":false,"trimmed":false,"spriteSourceSize":{"x":0,"y":0,"w":12,"h":12},"sourceSize":{"w":12,"h":12}},{"filename":"element_grey_polygon","frame":{"x":147,"y":298,"w":48,"h":46},"rotated":false,"trimmed":false,"spriteSourceSize":{"x":0,"y":0,"w":48,"h":46},"sourceSize":{"w":48,"h":46}},{"filename":"element_purple_diamond_glossy","frame":{"x":256,"y":0,"w":48,"h":48},"rotated":false,"trimmed":false,"spriteSourceSize":{"x":0,"y":0,"w":48,"h":48},"sourceSize":{"w":48,"h":48}},{"filename":"element_green_diamond","frame":{"x":256,"y":49,"w":48,"h":48},"rotated":false,"trimmed":false,"spriteSourceSize":{"x":0,"y":0,"w":48,"h":48},"sourceSize":{"w":48,"h":48}},{"filename":"element_grey_diamond","frame":{"x":256,"y":98,"w":48,"h":48},"rotated":false,"trimmed":false,"spriteSourceSize":{"x":0,"y":0,"w":48,"h":48},"sourceSize":{"w":48,"h":48}},{"filename":"element_grey_diamond_glossy","frame":{"x":256,"y":147,"w":48,"h":48},"rotated":false,"trimmed":false,"spriteSourceSize":{"x":0,"y":0,"w":48,"h":48},"sourceSize":{"w":48,"h":48}},{"filename":"element_green_square","frame":{"x":130,"y":183,"w":32,"h":32},"rotated":false,"trimmed":false,"spriteSourceSize":{"x":0,"y":0,"w":32,"h":32},"sourceSize":{"w":32,"h":32}},{"filename":"element_red_rectangle_glossy","frame":{"x":65,"y":216,"w":64,"h":32},"rotated":false,"trimmed":false,"spriteSourceSize":{"x":0,"y":0,"w":64,"h":32},"sourceSize":{"w":64,"h":32}},{"filename":"buttonSelected_right","frame":{"x":176,"y":150,"w":12,"h":12},"rotated":false,"trimmed":false,"spriteSourceSize":{"x":0,"y":0,"w":12,"h":12},"sourceSize":{"w":12,"h":12}},{"filename":"buttonSelected_mid","frame":{"x":105,"y":125,"w":12,"h":12},"rotated":false,"trimmed":false,"spriteSourceSize":{"x":0,"y":0,"w":12,"h":12},"sourceSize":{"w":12,"h":12}},{"filename":"buttonSelected_topright","frame":{"x":118,"y":125,"w":12,"h":12},"rotated":false,"trimmed":false,"spriteSourceSize":{"x":0,"y":0,"w":12,"h":12},"sourceSize":{"w":12,"h":12}},{"filename":"element_red_polygon","frame":{"x":196,"y":298,"w":48,"h":46},"rotated":false,"trimmed":false,"spriteSourceSize":{"x":0,"y":0,"w":48,"h":46},"sourceSize":{"w":48,"h":46}},{"filename":"element_yellow_diamond","frame":{"x":256,"y":196,"w":48,"h":48},"rotated":false,"trimmed":false,"spriteSourceSize":{"x":0,"y":0,"w":48,"h":48},"sourceSize":{"w":48,"h":48}},{"filename":"element_yellow_diamond_glossy","frame":{"x":256,"y":245,"w":48,"h":48},"rotated":false,"trimmed":false,"spriteSourceSize":{"x":0,"y":0,"w":48,"h":48},"sourceSize":{"w":48,"h":48}},{"filename":"element_blue_polygon","frame":{"x":245,"y":298,"w":48,"h":46},"rotated":false,"trimmed":false,"spriteSourceSize":{"x":0,"y":0,"w":48,"h":46},"sourceSize":{"w":48,"h":46}},{"filename":"element_blue_polygon_glossy","frame":{"x":305,"y":0,"w":48,"h":46},"rotated":false,"trimmed":false,"spriteSourceSize":{"x":0,"y":0,"w":48,"h":46},"sourceSize":{"w":48,"h":46}},{"filename":"selectorB","frame":{"x":305,"y":282,"w":38,"h":38},"rotated":false,"trimmed":false,"spriteSourceSize":{"x":0,"y":0,"w":38,"h":38},"sourceSize":{"w":38,"h":38}},{"filename":"element_yellow_rectangle","frame":{"x":191,"y":0,"w":64,"h":32},"rotated":false,"trimmed":false,"spriteSourceSize":{"x":0,"y":0,"w":64,"h":32},"sourceSize":{"w":64,"h":32}},{"filename":"element_yellow_rectangle_glossy","frame":{"x":191,"y":33,"w":64,"h":32},"rotated":false,"trimmed":false,"spriteSourceSize":{"x":0,"y":0,"w":64,"h":32},"sourceSize":{"w":64,"h":32}},{"filename":"element_red_polygon_glossy","frame":{"x":305,"y":47,"w":48,"h":46},"rotated":false,"trimmed":false,"spriteSourceSize":{"x":0,"y":0,"w":48,"h":46},"sourceSize":{"w":48,"h":46}},{"filename":"element_purple_polygon","frame":{"x":305,"y":94,"w":48,"h":46},"rotated":false,"trimmed":false,"spriteSourceSize":{"x":0,"y":0,"w":48,"h":46},"sourceSize":{"w":48,"h":46}},{"filename":"element_purple_polygon_glossy","frame":{"x":305,"y":141,"w":48,"h":46},"rotated":false,"trimmed":false,"spriteSourceSize":{"x":0,"y":0,"w":48,"h":46},"sourceSize":{"w":48,"h":46}},{"filename":"element_yellow_polygon","frame":{"x":305,"y":188,"w":48,"h":46},"rotated":false,"trimmed":false,"spriteSourceSize":{"x":0,"y":0,"w":48,"h":46},"sourceSize":{"w":48,"h":46}},{"filename":"element_yellow_polygon_glossy","frame":{"x":305,"y":235,"w":48,"h":46},"rotated":false,"trimmed":false,"spriteSourceSize":{"x":0,"y":0,"w":48,"h":46},"sourceSize":{"w":48,"h":46}},{"filename":"sprite78","frame":{"x":330,"y":368,"w":6,"h":6},"rotated":false,"trimmed":false,"spriteSourceSize":{"x":0,"y":0,"w":6,"h":6},"sourceSize":{"w":6,"h":6}},{"filename":"sprite79","frame":{"x":337,"y":368,"w":6,"h":6},"rotated":false,"trimmed":false,"spriteSourceSize":{"x":0,"y":0,"w":6,"h":6},"sourceSize":{"w":6,"h":6}},{"filename":"element_blue_square_glossy","frame":{"x":130,"y":150,"w":32,"h":32},"rotated":false,"trimmed":false,"spriteSourceSize":{"x":0,"y":0,"w":32,"h":32},"sourceSize":{"w":32,"h":32}},{"filename":"sprite80","frame":{"x":344,"y":368,"w":6,"h":6},"rotated":false,"trimmed":false,"spriteSourceSize":{"x":0,"y":0,"w":6,"h":6},"sourceSize":{"w":6,"h":6}},{"filename":"sprite81","frame":{"x":294,"y":320,"w":6,"h":6},"rotated":false,"trimmed":false,"spriteSourceSize":{"x":0,"y":0,"w":6,"h":6},"sourceSize":{"w":6,"h":6}},{"filename":"element_green_rectangle","frame":{"x":191,"y":66,"w":64,"h":32},"rotated":false,"trimmed":false,"spriteSourceSize":{"x":0,"y":0,"w":64,"h":32},"sourceSize":{"w":64,"h":32}},{"filename":"element_blue_rectangle","frame":{"x":191,"y":99,"w":64,"h":32},"rotated":false,"trimmed":false,"spriteSourceSize":{"x":0,"y":0,"w":64,"h":32},"sourceSize":{"w":64,"h":32}},{"filename":"element_blue_rectangle_glossy","frame":{"x":191,"y":132,"w":64,"h":32},"rotated":false,"trimmed":false,"spriteSourceSize":{"x":0,"y":0,"w":64,"h":32},"sourceSize":{"w":64,"h":32}},{"filename":"element_grey_rectangle","frame":{"x":191,"y":165,"w":64,"h":32},"rotated":false,"trimmed":false,"spriteSourceSize":{"x":0,"y":0,"w":64,"h":32},"sourceSize":{"w":64,"h":32}},{"filename":"buttonSelected_left","frame":{"x":131,"y":125,"w":12,"h":12},"rotated":false,"trimmed":false,"spriteSourceSize":{"x":0,"y":0,"w":12,"h":12},"sourceSize":{"w":12,"h":12}},{"filename":"buttonSelected_bottomright","frame":{"x":144,"y":125,"w":12,"h":12},"rotated":false,"trimmed":false,"spriteSourceSize":{"x":0,"y":0,"w":12,"h":12},"sourceSize":{"w":12,"h":12}},{"filename":"buttonDefault_bottomright","frame":{"x":157,"y":125,"w":12,"h":12},"rotated":false,"trimmed":false,"spriteSourceSize":{"x":0,"y":0,"w":12,"h":12},"sourceSize":{"w":12,"h":12}},{"filename":"buttonSelected_top","frame":{"x":170,"y":125,"w":12,"h":12},"rotated":false,"trimmed":false,"spriteSourceSize":{"x":0,"y":0,"w":12,"h":12},"sourceSize":{"w":12,"h":12}},{"filename":"buttonSelected_bottom","frame":{"x":105,"y":100,"w":12,"h":12},"rotated":false,"trimmed":false,"spriteSourceSize":{"x":0,"y":0,"w":12,"h":12},"sourceSize":{"w":12,"h":12}},{"filename":"element_grey_square","frame":{"x":0,"y":345,"w":32,"h":32},"rotated":false,"trimmed":false,"spriteSourceSize":{"x":0,"y":0,"w":32,"h":32},"sourceSize":{"w":32,"h":32}},{"filename":"element_purple_cube_glossy","frame":{"x":33,"y":345,"w":32,"h":32},"rotated":false,"trimmed":false,"spriteSourceSize":{"x":0,"y":0,"w":32,"h":32},"sourceSize":{"w":32,"h":32}},{"filename":"element_grey_square_glossy","frame":{"x":66,"y":345,"w":32,"h":32},"rotated":false,"trimmed":false,"spriteSourceSize":{"x":0,"y":0,"w":32,"h":32},"sourceSize":{"w":32,"h":32}},{"filename":"element_green_square_glossy","frame":{"x":99,"y":345,"w":32,"h":32},"rotated":false,"trimmed":false,"spriteSourceSize":{"x":0,"y":0,"w":32,"h":32},"sourceSize":{"w":32,"h":32}},{"filename":"element_purple_square","frame":{"x":132,"y":345,"w":32,"h":32},"rotated":false,"trimmed":false,"spriteSourceSize":{"x":0,"y":0,"w":32,"h":32},"sourceSize":{"w":32,"h":32}},{"filename":"element_red_square","frame":{"x":165,"y":345,"w":32,"h":32},"rotated":false,"trimmed":false,"spriteSourceSize":{"x":0,"y":0,"w":32,"h":32},"sourceSize":{"w":32,"h":32}},{"filename":"element_red_square_glossy","frame":{"x":198,"y":345,"w":32,"h":32},"rotated":false,"trimmed":false,"spriteSourceSize":{"x":0,"y":0,"w":32,"h":32},"sourceSize":{"w":32,"h":32}},{"filename":"element_yellow_square","frame":{"x":231,"y":345,"w":32,"h":32},"rotated":false,"trimmed":false,"spriteSourceSize":{"x":0,"y":0,"w":32,"h":32},"sourceSize":{"w":32,"h":32}},{"filename":"element_yellow_square_glossy","frame":{"x":264,"y":345,"w":32,"h":32},"rotated":false,"trimmed":false,"spriteSourceSize":{"x":0,"y":0,"w":32,"h":32},"sourceSize":{"w":32,"h":32}},{"filename":"selectorC","frame":{"x":297,"y":345,"w":32,"h":32},"rotated":false,"trimmed":false,"spriteSourceSize":{"x":0,"y":0,"w":32,"h":32},"sourceSize":{"w":32,"h":32}},{"filename":"buttonDefault_topright","frame":{"x":118,"y":100,"w":12,"h":12},"rotated":false,"trimmed":false,"spriteSourceSize":{"x":0,"y":0,"w":12,"h":12},"sourceSize":{"w":12,"h":12}},{"filename":"buttonSelected_bottomleft","frame":{"x":131,"y":100,"w":12,"h":12},"rotated":false,"trimmed":false,"spriteSourceSize":{"x":0,"y":0,"w":12,"h":12},"sourceSize":{"w":12,"h":12}},{"filename":"particleSmallStar","frame":{"x":294,"y":298,"w":10,"h":10},"rotated":false,"trimmed":false,"spriteSourceSize":{"x":0,"y":0,"w":10,"h":10},"sourceSize":{"w":10,"h":10}},{"filename":"paddleBlu","frame":{"x":0,"y":100,"w":104,"h":24},"rotated":false,"trimmed":false,"spriteSourceSize":{"x":0,"y":0,"w":104,"h":24},"sourceSize":{"w":104,"h":24}},{"filename":"paddleRed","frame":{"x":0,"y":125,"w":104,"h":24},"rotated":false,"trimmed":false,"spriteSourceSize":{"x":0,"y":0,"w":104,"h":24},"sourceSize":{"w":104,"h":24}},{"filename":"ballBlue","frame":{"x":330,"y":345,"w":22,"h":22},"rotated":false,"trimmed":false,"spriteSourceSize":{"x":0,"y":0,"w":22,"h":22},"sourceSize":{"w":22,"h":22}},{"filename":"ballGrey","frame":{"x":163,"y":216,"w":22,"h":22},"rotated":false,"trimmed":false,"spriteSourceSize":{"x":0,"y":0,"w":22,"h":22},"sourceSize":{"w":22,"h":22}},{"filename":"particleStar","frame":{"x":163,"y":183,"w":20,"h":21},"rotated":false,"trimmed":false,"spriteSourceSize":{"x":0,"y":0,"w":20,"h":21},"sourceSize":{"w":20,"h":21}},{"filename":"buttonDefault_left","frame":{"x":144,"y":100,"w":12,"h":12},"rotated":false,"trimmed":false,"spriteSourceSize":{"x":0,"y":0,"w":12,"h":12},"sourceSize":{"w":12,"h":12}},{"filename":"buttonDefault_mid","frame":{"x":157,"y":100,"w":12,"h":12},"rotated":false,"trimmed":false,"spriteSourceSize":{"x":0,"y":0,"w":12,"h":12},"sourceSize":{"w":12,"h":12}},{"filename":"buttonDefault_right","frame":{"x":170,"y":100,"w":12,"h":12},"rotated":false,"trimmed":false,"spriteSourceSize":{"x":0,"y":0,"w":12,"h":12},"sourceSize":{"w":12,"h":12}},{"filename":"buttonDefault_top","frame":{"x":240,"y":198,"w":12,"h":12},"rotated":false,"trimmed":false,"spriteSourceSize":{"x":0,"y":0,"w":12,"h":12},"sourceSize":{"w":12,"h":12}},{"filename":"buttonDefault_topleft","frame":{"x":240,"y":211,"w":12,"h":12},"rotated":false,"trimmed":false,"spriteSourceSize":{"x":0,"y":0,"w":12,"h":12},"sourceSize":{"w":12,"h":12}},{"filename":"particleCartoonStar","frame":{"x":294,"y":309,"w":10,"h":10},"rotated":false,"trimmed":false,"spriteSourceSize":{"x":0,"y":0,"w":10,"h":10},"sourceSize":{"w":10,"h":10}}],"meta":{"app":"https://www.leshylabs.com/apps/sstool/","version":"Leshy SpriteSheet Tool v0.8.4","image":"spritesheet.png","size":{"w":353,"h":377},"scale":1}}